odd_even_checker/checker.py
odd_even_checker/init.py
vismaya_odd_even_checker-0.0.1.dist-info/licenses/LICENSE
vismaya_odd_even_checker-0.0.1.dist-info/METADATA
vismaya_odd_even_checker-0.0.1.dist-info/WHEEL
vismaya_odd_even_checker-0.0.1.dist-info/top_level.txt
vismaya_odd_even_checker-0.0.1.dist-info/RECORD
