Metadata-Version: 2.4
Name: vismaya-odd-even-checker
Version: 0.0.1
Summary: A simple Python library to check odd or even numbers
Author-email: Vismaya_M_S <msvismaya05@gmail.com>
License: MIT License
Requires-Python: >=3.7
License-File: LICENSE
Dynamic: license-file
